signal_themer/__main__.py
signal_themer-1.1.dist-info/LICENSE
signal_themer-1.1.dist-info/METADATA
signal_themer-1.1.dist-info/WHEEL
signal_themer-1.1.dist-info/entry_points.txt
signal_themer-1.1.dist-info/top_level.txt
signal_themer-1.1.dist-info/RECORD
