Metadata-Version: 2.1
Name: signal-themer
Version: 1.1
Summary: Theme injector for signal-desktop
Home-page: https://github.com/CalfMoon/signal-themer
Author: Kritagya Bhattarai(CalfMoon)
Author-email: kritagyabhattarai@proton.me
Classifier: Programming Language :: Python :: 3
Classifier: Environment :: Console
Classifier: Intended Audience :: End Users/Desktop
Classifier: License :: OSI Approved :: GNU General Public License (GPL)
Classifier: Operating System :: OS Independent
License-File: LICENSE
Requires-Dist: asarPy
